LICENSE.txt
MANIFEST.in
README.rst
setup.cfg
setup.py
atl_django_component/__init__.py
atl_django_component/component.py
atl_django_component.egg-info/PKG-INFO
atl_django_component.egg-info/SOURCES.txt
atl_django_component.egg-info/dependency_links.txt
atl_django_component.egg-info/pbr.json
atl_django_component.egg-info/requires.txt
atl_django_component.egg-info/top_level.txt
atl_django_component/templates/atl_django_component/component.html
atl_django_component/templatetags/__init__.py
atl_django_component/templatetags/atl_django_component.py