Metadata-Version: 1.1
Name: atl-django-component
Version: 0.1.dev7
Summary: An initiative to encapsulate components in django
Home-page: https://bitbucket.org/atlantesoftware/atl-django-component
Author: Hailem Dreis Carrasco Fuentes
Author-email: hailem@gmail.com
License: GNU GPLv3
Keywords: django component
Platform: UNKNOWN
Classifier: Development Status :: 4 - Beta
Classifier: Intended Audience :: Developers
Classifier: Programming Language :: Python
Classifier: Framework :: Django
Classifier: Environment :: Web Environment
Classifier: Topic :: Utilities
Classifier: License :: OSI Approved :: GNU General Public License v3 (GPLv3)
Classifier: Operating System :: OS Independent
Classifier: Topic :: Internet :: WWW/HTTP :: Dynamic Content
Classifier: Topic :: Software Development
Classifier: Topic :: Software Development :: Libraries :: Application Frameworks
Classifier: Topic :: Software Development :: Libraries :: Python Modules
